odoo/addons/barcodes_generator_location/README.rst
odoo/addons/barcodes_generator_location/__init__.py
odoo/addons/barcodes_generator_location/__manifest__.py
odoo/addons/barcodes_generator_location/hooks.py
odoo/addons/barcodes_generator_location/demo/barcode_rule.xml
odoo/addons/barcodes_generator_location/demo/function.xml
odoo/addons/barcodes_generator_location/demo/ir_sequence.xml
odoo/addons/barcodes_generator_location/demo/stock_location.xml
odoo/addons/barcodes_generator_location/i18n/barcodes_generator_location.pot
odoo/addons/barcodes_generator_location/i18n/es.po
odoo/addons/barcodes_generator_location/i18n/fr.po
odoo/addons/barcodes_generator_location/i18n/hr.po
odoo/addons/barcodes_generator_location/i18n/nl_NL.po
odoo/addons/barcodes_generator_location/models/__init__.py
odoo/addons/barcodes_generator_location/models/barcode_rule.py
odoo/addons/barcodes_generator_location/models/stock_location.py
odoo/addons/barcodes_generator_location/readme/CONFIGURE.rst
odoo/addons/barcodes_generator_location/readme/CONTRIBUTORS.rst
odoo/addons/barcodes_generator_location/readme/CREDITS.rst
odoo/addons/barcodes_generator_location/readme/DESCRIPTION.rst
odoo/addons/barcodes_generator_location/readme/USAGE.rst
odoo/addons/barcodes_generator_location/static/description/icon.png
odoo/addons/barcodes_generator_location/static/description/index.html
odoo/addons/barcodes_generator_location/static/description/stock_location_sequence_generation.png
odoo/addons/barcodes_generator_location/tests/__init__.py
odoo/addons/barcodes_generator_location/tests/test_barcode_generator.py
odoo/addons/barcodes_generator_location/views/stock_location.xml
odoo12_addon_barcodes_generator_location-12.0.1.0.1.dist-info/METADATA
odoo12_addon_barcodes_generator_location-12.0.1.0.1.dist-info/WHEEL
odoo12_addon_barcodes_generator_location-12.0.1.0.1.dist-info/top_level.txt
odoo12_addon_barcodes_generator_location-12.0.1.0.1.dist-info/RECORD
